UR2CUTE/__init__.py
UR2CUTE/model.py
UR2CUTE/py.typed
ur2cute-0.1.8.dist-info/licenses/LICENSE
ur2cute-0.1.8.dist-info/METADATA
ur2cute-0.1.8.dist-info/WHEEL
ur2cute-0.1.8.dist-info/top_level.txt
ur2cute-0.1.8.dist-info/RECORD
