Metadata-Version: 2.4
Name: UR2CUTE
Version: 0.1.8
Summary: A time-series forecasting model using UR2CUTE: Using Repetitively 2 CNN for Unsteady Timeseries Estimation
Author: Patrick Brandtner, Zuzana Komínková Oplatková, Taha Falatouri, Mehran Naseri, Farzaneh Darbanian
Author-email: Sina Mirshahi <sina7th@gmail.com>
Maintainer-email: Sina Mirshahi <sina7th@gmail.com>
License-Expression: MIT
Project-URL: Homepage, https://github.com/FH-Prevail/UR2CUTE_torch
Project-URL: Repository, https://github.com/FH-Prevail/UR2CUTE_torch
Project-URL: Documentation, https://github.com/FH-Prevail/UR2CUTE_torch#readme
Project-URL: Bug Tracker, https://github.com/FH-Prevail/UR2CUTE_torch/issues
Project-URL: Changelog, https://github.com/FH-Prevail/UR2CUTE_torch/blob/main/CHANGES.md
Keywords: time-series,forecasting,intermittent-demand,CNN,deep-learning,pytorch,machine-learning,demand-forecasting,inventory-management
Classifier: Development Status :: 4 - Beta
Classifier: Intended Audience :: Science/Research
Classifier: Intended Audience :: Developers
Classifier: Operating System :: OS Independent
Classifier: Programming Language :: Python :: 3
Classifier: Programming Language :: Python :: 3.7
Classifier: Programming Language :: Python :: 3.8
Classifier: Programming Language :: Python :: 3.9
Classifier: Programming Language :: Python :: 3.10
Classifier: Programming Language :: Python :: 3.11
Classifier: Programming Language :: Python :: 3.12
Classifier: Topic :: Scientific/Engineering :: Artificial Intelligence
Classifier: Topic :: Software Development :: Libraries :: Python Modules
Requires-Python: >=3.7
License-File: LICENSE
Requires-Dist: numpy>=1.19.0
Requires-Dist: pandas>=1.1.0
Requires-Dist: torch>=1.7.0
Requires-Dist: scikit-learn>=0.24.0
Provides-Extra: dev
Requires-Dist: pytest>=7.0.0; extra == "dev"
Requires-Dist: pytest-cov>=3.0.0; extra == "dev"
Requires-Dist: black>=22.0.0; extra == "dev"
Requires-Dist: flake8>=4.0.0; extra == "dev"
Requires-Dist: mypy>=0.950; extra == "dev"
Requires-Dist: isort>=5.10.0; extra == "dev"
Provides-Extra: test
Requires-Dist: pytest>=7.0.0; extra == "test"
Requires-Dist: pytest-cov>=3.0.0; extra == "test"
Provides-Extra: docs
Requires-Dist: sphinx>=4.0.0; extra == "docs"
Requires-Dist: sphinx-rtd-theme>=1.0.0; extra == "docs"
Requires-Dist: sphinxcontrib-napoleon>=0.7; extra == "docs"
Dynamic: license-file
